mibig/__init__.py
mibig/converters/__init__.py
mibig/converters/read/__init__.py
mibig/converters/read/alkaloid.py
mibig/converters/read/cluster.py
mibig/converters/read/nrp.py
mibig/converters/read/other.py
mibig/converters/read/polyketide.py
mibig/converters/read/ripp.py
mibig/converters/read/saccharide.py
mibig/converters/read/shared.py
mibig/converters/read/terpene.py
mibig/converters/read/top.py
mibig/converters/to/__init__.py
mibig/converters/to/alkaloid.py
mibig/converters/to/cluster.py
mibig/converters/to/nrp.py
mibig/converters/to/other.py
mibig/converters/to/polyketide.py
mibig/converters/to/ripp.py
mibig/converters/to/saccharide.py
mibig/converters/to/shared.py
mibig/converters/to/terpene.py
mibig/converters/to/top.py
mibig_data/__init__.py
mibig_data/converters/__init__.py
mibig_data/converters/read/__init__.py
mibig_data/converters/read/alkaloid.py
mibig_data/converters/read/cluster.py
mibig_data/converters/read/nrp.py
mibig_data/converters/read/other.py
mibig_data/converters/read/polyketide.py
mibig_data/converters/read/ripp.py
mibig_data/converters/read/saccharide.py
mibig_data/converters/read/shared.py
mibig_data/converters/read/terpene.py
mibig_data/converters/read/top.py
mibig_data/converters/to/__init__.py
mibig_data/converters/to/alkaloid.py
mibig_data/converters/to/cluster.py
mibig_data/converters/to/nrp.py
mibig_data/converters/to/other.py
mibig_data/converters/to/polyketide.py
mibig_data/converters/to/ripp.py
mibig_data/converters/to/saccharide.py
mibig_data/converters/to/shared.py
mibig_data/converters/to/terpene.py
mibig_data/converters/to/top.py
python_mibig-0.1.0.dist-info/LICENSE.txt
python_mibig-0.1.0.dist-info/METADATA
python_mibig-0.1.0.dist-info/WHEEL
python_mibig-0.1.0.dist-info/top_level.txt
python_mibig-0.1.0.dist-info/RECORD
